coverage_pyver_pragma/__init__.py
coverage_pyver_pragma/grammar.py
coverage_pyver_pragma/py.typed
coverage_pyver_pragma-0.3.3.dist-info/LICENSE
coverage_pyver_pragma-0.3.3.dist-info/METADATA
coverage_pyver_pragma-0.3.3.dist-info/WHEEL
coverage_pyver_pragma-0.3.3.dist-info/entry_points.txt
coverage_pyver_pragma-0.3.3.dist-info/RECORD
