Metadata-Version: 2.2
Name: coverage-pyver-pragma
Version: 0.3.3
Summary: Plugin for Coverage.py to selectively ignore branches depending on the Python version.
Author-email: Dominic Davis-Foster <dominic@davis-foster.co.uk>
License: MIT
Keywords: coverage
Home-page: https://github.com/python-coincidence/coverage_pyver_pragma
Project-URL: Issue Tracker, https://github.com/python-coincidence/coverage_pyver_pragma/issues
Project-URL: Source Code, https://github.com/python-coincidence/coverage_pyver_pragma
Project-URL: Documentation, https://coverage-pyver-pragma.readthedocs.io/en/latest
Platform: Windows
Platform: macOS
Platform: Linux
Classifier: Development Status :: 4 - Beta
Classifier: Intended Audience :: Developers
Classifier: License :: OSI Approved :: MIT License
Classifier: Operating System :: OS Independent
Classifier: Programming Language :: Python
Classifier: Programming Language :: Python :: 3 :: Only
Classifier: Programming Language :: Python :: 3.6
Classifier: Programming Language :: Python :: 3.7
Classifier: Programming Language :: Python :: 3.8
Classifier: Programming Language :: Python :: 3.9
Classifier: Programming Language :: Python :: 3.10
Classifier: Programming Language :: Python :: 3.11
Classifier: Programming Language :: Python :: 3.12
Classifier: Programming Language :: Python :: Implementation :: CPython
Classifier: Programming Language :: Python :: Implementation :: PyPy
Classifier: Topic :: Utilities
Classifier: Typing :: Typed
Requires-Python: >=3.6
Requires-Dist: coverage>=5.5
Requires-Dist: domdf-python-tools>=2.8.0
Requires-Dist: packaging>=20.9
Requires-Dist: pyparsing>=2.4.7
